unitpy/__init__.py
unitpy/config.py
unitpy/core.py
unitpy/errors.py
unitpy/numpy_funcs.py
unitpy/definitions/__init__.py
unitpy/definitions/constants.py
unitpy/definitions/dimensions.py
unitpy/definitions/entry.py
unitpy/definitions/ledger.py
unitpy/definitions/metric.py
unitpy/definitions/prefix.py
unitpy/definitions/unit_NIST.py
unitpy/definitions/unit_base.py
unitpy/definitions/unit_derived.py
unitpy/definitions/unit_extra.py
unitpy/utils/__init__.py
unitpy/utils/equation_formating.py
unitpy/utils/parsing.py
unitpy/utils/string_converter.py
unitpy-0.0.19.dist-info/LICENSE.txt
unitpy-0.0.19.dist-info/METADATA
unitpy-0.0.19.dist-info/WHEEL
unitpy-0.0.19.dist-info/top_level.txt
unitpy-0.0.19.dist-info/RECORD
