Metadata-Version: 2.2
Name: unitpy
Version: 0.0.19
Summary: Working with scientific units in python.
Home-page: https://github.com/dylanwal/unitpy
Author: Dylan Walsh
License: BSD
Platform: any
Classifier: Intended Audience :: Science/Research
Classifier: Topic :: Scientific/Engineering
Classifier: License :: OSI Approved :: BSD License
Classifier: Programming Language :: Python
Classifier: Programming Language :: Python :: 3 :: Only
Classifier: Programming Language :: Python :: 3.8
Classifier: Programming Language :: Python :: 3.9
Classifier: Programming Language :: Python :: 3.10
Classifier: Programming Language :: Python :: 3.11
Requires-Python: >=3.8
License-File: LICENSE.txt
